smartwidgets/__init__.py
smartwidgets/widgets.py
smartwidgets-0.0.2.dist-info/LICENSE
smartwidgets-0.0.2.dist-info/METADATA
smartwidgets-0.0.2.dist-info/WHEEL
smartwidgets-0.0.2.dist-info/top_level.txt
smartwidgets-0.0.2.dist-info/RECORD
